vacances_scolaires_france/__init__.py
vacances_scolaires_france/data/data.csv
vacances_scolaires_france-0.11.0.dist-info/licenses/LICENSE.md
vacances_scolaires_france-0.11.0.dist-info/METADATA
vacances_scolaires_france-0.11.0.dist-info/WHEEL
vacances_scolaires_france-0.11.0.dist-info/top_level.txt
vacances_scolaires_france-0.11.0.dist-info/RECORD
