Metadata-Version: 2.4
Name: vacances_scolaires_france
Version: 0.11.0
Summary: Get school holiday dates for metropolitan France
Home-page: https://github.com/AntoineAugusti/vacances-scolaires-france
Author: Antoine Augusti
Author-email: hi@antoine-augusti.fr
License: MIT
Keywords: vacances,scolaires,calendrier,france,school,holiday,calendar
Classifier: Development Status :: 3 - Alpha
Classifier: Intended Audience :: Developers
Classifier: License :: OSI Approved :: MIT License
Classifier: Programming Language :: Python :: 2.7
Classifier: Programming Language :: Python :: 3
Requires-Python: >=2.7, <4
License-File: LICENSE.md
Provides-Extra: dev
Requires-Dist: pytest; extra == "dev"
Dynamic: author
Dynamic: author-email
Dynamic: classifier
Dynamic: description
Dynamic: description-content-type
Dynamic: home-page
Dynamic: keywords
Dynamic: license
Dynamic: license-file
Dynamic: provides-extra
Dynamic: requires-python
Dynamic: summary
